arithmetic/__init__.py
arithmetic/addition.py
arithmetic/draft/addition_3.py
arithmetic/draft/addition_4.py
example_pkg_rsecon25-0.1.0.dist-info/licenses/LICENSE
genomics/__init__.py
genomics/annotation.py
genomics/draft/annotation_2.py
example_pkg_rsecon25-0.1.0.dist-info/METADATA
example_pkg_rsecon25-0.1.0.dist-info/WHEEL
example_pkg_rsecon25-0.1.0.dist-info/top_level.txt
example_pkg_rsecon25-0.1.0.dist-info/RECORD
